yta_voice_assistant/__init__.py
yta_voice_assistant/wit.py
yta_voice_assistant/audio/__init__.py
yta_voice_assistant/audio/narration.py
yta_voice_assistant/audio/sound.py
yta_voice_assistant/audio/sounds/__init__.py
yta_voice_assistant/audio/speech/__init__.py
yta_voice_assistant/audio/speech/detector.py
yta_voice_assistant-0.0.13.dist-info/LICENSE
yta_voice_assistant-0.0.13.dist-info/METADATA
yta_voice_assistant-0.0.13.dist-info/WHEEL
yta_voice_assistant-0.0.13.dist-info/top_level.txt
yta_voice_assistant-0.0.13.dist-info/RECORD
