Metadata-Version: 2.2
Name: yta_voice_assistant
Version: 0.0.13
Summary: Youtube Autonomous Voice Assistant.
Author: Daniel Alcalá
Author-email: <danielalcalavalera@gmail.com>
Keywords: youtube autonomous voice assistant software
Classifier: Development Status :: 3 - Alpha
Classifier: Intended Audience :: Education
Classifier: Programming Language :: Python :: 2
Classifier: Programming Language :: Python :: 3
Classifier: Operating System :: MacOS :: MacOS X
Classifier: Operating System :: Microsoft :: Windows
License-File: LICENSE
Requires-Dist: yta_audio
Requires-Dist: yta_general_utils
Dynamic: author
Dynamic: author-email
Dynamic: classifier
Dynamic: description
Dynamic: keywords
Dynamic: requires-dist
Dynamic: summary
